gcndesign/__init__.py
gcndesign/dataset.py
gcndesign/hypara.py
gcndesign/models.py
gcndesign/pdbutil.py
gcndesign/predictor.py
gcndesign/resfile.py
gcndesign/training.py
gcndesign/params/param_default.pkl
gcndesign/params/param_legacy_06.15.2021
gcndesign-2.3.2.data/scripts/gcndesign_autodesign.py
gcndesign-2.3.2.data/scripts/gcndesign_pdb2pkl.py
gcndesign-2.3.2.data/scripts/gcndesign_predict.py
gcndesign-2.3.2.data/scripts/gcndesign_resfile.py
gcndesign-2.3.2.data/scripts/gcndesign_test.py
gcndesign-2.3.2.data/scripts/gcndesign_training.py
gcndesign-2.3.2.dist-info/LICENSE
gcndesign-2.3.2.dist-info/METADATA
gcndesign-2.3.2.dist-info/WHEEL
gcndesign-2.3.2.dist-info/top_level.txt
gcndesign-2.3.2.dist-info/RECORD
