Metadata-Version: 2.1
Name: gcndesign
Version: 2.3.2
Summary: Neural network model for predicting amino-acid sequence from a protein backbone structure
Home-page: https://github.com/ShintaroMinami/GCNdesign
Author: Shintaro Minami
License: MIT
Keywords: gcndesign,autodesign
Classifier: License :: OSI Approved :: MIT License
Classifier: Programming Language :: Python :: 3.8
License-File: LICENSE
Requires-Dist: numpy
Requires-Dist: pandas
Requires-Dist: torch
Requires-Dist: tqdm
